.clang-format
.gitignore
LICENSE
README.md
mypy.ini
pyproject.toml
setup.cfg
setup.py
.github/dependabot.yml
.github/workflows/build_docs.yml
.github/workflows/pyopendds.yml
docs/.gitignore
docs/Makefile
docs/conf.py
docs/getting_started.rst
docs/index.rst
docs/make.bat
docs/modules.rst
docs/proposed_idl_mapping.rst
docs/requirements.txt
pyopendds/DataReader.py
pyopendds/DataWriter.py
pyopendds/DomainParticipant.py
pyopendds/Publisher.py
pyopendds/Subscriber.py
pyopendds/Topic.py
pyopendds/__init__.py
pyopendds/constants.py
pyopendds/exceptions.py
pyopendds/init_opendds.py
pyopendds/util.py
pyopendds.egg-info/PKG-INFO
pyopendds.egg-info/SOURCES.txt
pyopendds.egg-info/dependency_links.txt
pyopendds.egg-info/entry_points.txt
pyopendds.egg-info/requires.txt
pyopendds.egg-info/top_level.txt
pyopendds/dev/__init__.py
pyopendds/dev/util.py
pyopendds/dev/include/pyopendds/common.hpp
pyopendds/dev/include/pyopendds/user.hpp
pyopendds/dev/itl2py/CppOutput.py
pyopendds/dev/itl2py/Output.py
pyopendds/dev/itl2py/PythonOutput.py
pyopendds/dev/itl2py/__init__.py
pyopendds/dev/itl2py/__main__.py
pyopendds/dev/itl2py/ast.py
pyopendds/dev/itl2py/generate.py
pyopendds/dev/itl2py/itl.py
pyopendds/dev/itl2py/templates/CMakeLists.txt
pyopendds/dev/itl2py/templates/setup.py
pyopendds/dev/itl2py/templates/user.cpp
pyopendds/dev/itl2py/templates/user.py
pyopendds/ext/CMakeLists.txt
pyopendds/ext/_pyopendds.cpp
tests/run_tests.py
tests/basic_test/.gitignore
tests/basic_test/CMakeLists.txt
tests/basic_test/basic.idl
tests/basic_test/publisher.cpp
tests/basic_test/rtps.ini
tests/basic_test/run_test.py
tests/basic_test/run_test.sh
tests/basic_test/subscriber.py
tests/itl2py_test/.gitignore
tests/itl2py_test/CMakeLists.txt
tests/itl2py_test/another_file.idl
tests/itl2py_test/itl2py_test.idl
tests/unit_tests/__init__.py
tests/unit_tests/test_opendds_version.py