Metadata-Version: 2.1
Name: pyopendds
Version: 0.2.0
Summary: Python Bindings for OpenDDS
Home-page: https://github.com/oci-labs/pyopendds
Author: Fred Hornsey
Author-email: hornseyf@objectcomputing.com
License: MIT
Keywords: opendds dds
Platform: UNKNOWN
Classifier: License :: OSI Approved :: MIT License
Classifier: Development Status :: 2 - Pre-Alpha
Classifier: Intended Audience :: Developers
Classifier: Programming Language :: C++
Classifier: Programming Language :: Python :: 3
Classifier: Programming Language :: Python :: 3.7
Classifier: Programming Language :: Python :: 3.8
Classifier: Programming Language :: Python :: 3.9
Classifier: Programming Language :: Python :: 3.10
Classifier: Programming Language :: Python :: 3.11
Classifier: Programming Language :: Python :: Implementation :: CPython
Classifier: Topic :: Communications
Classifier: Topic :: Software Development :: Code Generators
Classifier: Topic :: Software Development :: Libraries
License-File: LICENSE
